xarray_spatial-0.5.2.dist-info/licenses/LICENSE.txt
xrspatial/__init__.py
xrspatial/__main__.py
xrspatial/_version.py
xrspatial/analytics.py
xrspatial/aspect.py
xrspatial/bump.py
xrspatial/classify.py
xrspatial/convolution.py
xrspatial/curvature.py
xrspatial/esri.py
xrspatial/focal.py
xrspatial/hillshade.py
xrspatial/local.py
xrspatial/multispectral.py
xrspatial/pathfinding.py
xrspatial/perlin.py
xrspatial/proximity.py
xrspatial/slope.py
xrspatial/terrain.py
xrspatial/utils.py
xrspatial/viewshed.py
xrspatial/zonal.py
xrspatial/datasets/__init__.py
xrspatial/datasets/sentinel-2/blue_band.nc
xrspatial/datasets/sentinel-2/green_band.nc
xrspatial/datasets/sentinel-2/nir_band.nc
xrspatial/datasets/sentinel-2/red_band.nc
xrspatial/datasets/sentinel-2/swir1_band.nc
xrspatial/datasets/sentinel-2/swir2_band.nc
xrspatial/examples/Pathfinding_Austin_Road_Network.ipynb
xrspatial/examples/animated_hillshade.py
xrspatial/examples/cloudless-mosaic-sentinel2.ipynb
xrspatial/examples/composite_map.gif
xrspatial/examples/datasets.yml
xrspatial/examples/housing_price_feature_engineering.ipynb
xrspatial/examples/pharmacy-deserts.ipynb
xrspatial/examples/viewshed_gpu.ipynb
xrspatial/examples/xarray-spatial_classification-methods.ipynb
xrspatial/examples/user_guide/0_Getting_Setup.ipynb
xrspatial/examples/user_guide/1_Surface.ipynb
xrspatial/examples/user_guide/2_Proximity.ipynb
xrspatial/examples/user_guide/3_Zonal.ipynb
xrspatial/examples/user_guide/4_Focal.ipynb
xrspatial/examples/user_guide/5_Classification.ipynb
xrspatial/examples/user_guide/6_Remote_Sensing.ipynb
xrspatial/examples/user_guide/7_Pathfinding.ipynb
xrspatial/examples/user_guide/8_Local_Tools.ipynb
xrspatial/examples/user_guide/zonal_crosstab.ipynb
xrspatial/experimental/__init__.py
xrspatial/experimental/polygonize.py
xrspatial/gpu_rtx/__init__.py
xrspatial/gpu_rtx/cuda_utils.py
xrspatial/gpu_rtx/hillshade.py
xrspatial/gpu_rtx/mesh_utils.py
xrspatial/gpu_rtx/viewshed.py
xrspatial/tests/__init__.py
xrspatial/tests/conftest.py
xrspatial/tests/general_checks.py
xarray_spatial-0.5.2.dist-info/METADATA
xarray_spatial-0.5.2.dist-info/WHEEL
xarray_spatial-0.5.2.dist-info/entry_points.txt
xarray_spatial-0.5.2.dist-info/top_level.txt
xarray_spatial-0.5.2.dist-info/RECORD
