Metadata-Version: 2.4
Name: xarray-spatial
Version: 0.5.2
Summary: xarray-based spatial analysis tools
Home-page: https://github.com/makepath/xarray-spatial
Author: makepath
License: MIT
Platform: any
Classifier: Development Status :: 4 - Beta
Classifier: Intended Audience :: Developers
Classifier: Intended Audience :: Science/Research
Classifier: License :: OSI Approved :: MIT License
Classifier: Operating System :: OS Independent
Classifier: Programming Language :: Python :: 3
Requires-Python: >=3.8
License-File: LICENSE.txt
Requires-Dist: datashader>=0.15.0
Requires-Dist: numba
Requires-Dist: xarray
Requires-Dist: numpy
Provides-Extra: doc
Requires-Dist: dask[dataframe]; extra == "doc"
Requires-Dist: geopandas; extra == "doc"
Requires-Dist: Jinja2>=2.11; extra == "doc"
Requires-Dist: ipykernel; extra == "doc"
Requires-Dist: matplotlib; extra == "doc"
Requires-Dist: nbsphinx; extra == "doc"
Requires-Dist: numpydoc; extra == "doc"
Requires-Dist: pandoc; extra == "doc"
Requires-Dist: pydata_sphinx_theme; extra == "doc"
Requires-Dist: sphinx; extra == "doc"
Requires-Dist: sphinx-panels; extra == "doc"
Requires-Dist: sphinx_rtd_theme; extra == "doc"
Provides-Extra: examples
Provides-Extra: optional
Requires-Dist: awkward>=1.4; extra == "optional"
Requires-Dist: geopandas; extra == "optional"
Requires-Dist: shapely; extra == "optional"
Requires-Dist: spatialpandas; extra == "optional"
Requires-Dist: rtxpy; extra == "optional"
Provides-Extra: tests
Requires-Dist: flake8; extra == "tests"
Requires-Dist: isort; extra == "tests"
Requires-Dist: noise>=1.2.2; extra == "tests"
Requires-Dist: dask; extra == "tests"
Requires-Dist: pyarrow; extra == "tests"
Requires-Dist: pytest; extra == "tests"
Requires-Dist: pytest-cov; extra == "tests"
Dynamic: license-file
